Workbook

Sheet Tableau de bord
A1: LE YELLOW JACK — Tableau de bord
A2: Vue d'ensemble de la comptabilite du bar
A4: Legende : cellules bleues = a completer / choisir. Le reste se calcule tout seul.
A6: Periode analysee (mois) | B6: =TODAY()
A8: RECETTES
A9: Total des ventes (bar) | B9: =SUM(Ventes!G5:G201)
A11: DEPENSES
A12: Total des achats / depenses | B12: =SUM(Depenses!D5:D201)
A13: Total des salaires verses | B13: =SUM(Salaires!F5:F200)
A14: Total des depenses (achats + salaires) | B14: =B12+B13
A16: RESULTAT
A17: Benefice net | B17: =B9-B14
A18: Marge nette (%) | B18: =IFERROR(B17/B9,0)
A20: CAISSE / STOCK
A21: Valeur du stock actuel (prix d'achat) | B21: =SUMPRODUCT(Stock!C5:C203,Stock!E5:E203)
A22: Nombre d'articles sous le seuil d'alerte | B22: =SUMPRODUCT(ISNUMBER(Stock!C5:C203)*ISNUMBER(Stock!D5:D203)*(Stock!C5:C203<=Stock!D5:D203))

Sheet Ventes
A1: Ventes — Le Yellow Jack
A4: Date | B4: Employe | C4: Article vendu | D4: Categorie | E4: Quantite | F4: Prix unitaire | G4: Total
A5: 46287 | B5: Test | C5: Jus d’orange | D5: Boisson | E5: X | F5: X | G5: =IFERROR(IF(E5="","",E5*F5),"")
A6: 46287 | B6: Test | C6: Jus d’orange | D6: Boisson | E6: X | F6: X | G6: =IFERROR(IF(E6="","",E6*F6),"")
G7: =IFERROR(IF(E7="","",E7*F7),"")
G8: =IFERROR(IF(E8="","",E8*F8),"")
G9: =IFERROR(IF(E9="","",E9*F9),"")
G10: =IFERROR(IF(E10="","",E10*F10),"")
G11: =IFERROR(IF(E11="","",E11*F11),"")
G12: =IFERROR(IF(E12="","",E12*F12),"")
G13: =IFERROR(IF(E13="","",E13*F13),"")
G14: =IFERROR(IF(E14="","",E14*F14),"")
G15: =IFERROR(IF(E15="","",E15*F15),"")
G16: =IFERROR(IF(E16="","",E16*F16),"")
G17: =IFERROR(IF(E17="","",E17*F17),"")
G18: =IFERROR(IF(E18="","",E18*F18),"")
... G201: =IFERROR(IF(E201="","",E201*F201),"")

Sheet Depenses
A1: Depenses — Le Yellow Jack
A2: Achats de stock, decoration, reparations, licences...
A4: Date | B4: Categorie | C4: Description | D4: Montant
A5: 46287 | B5: Stock alcool | C5: Test | D5: X
A6: 46288 | B6: Entretien | C6: Test | D6: X

Sheet Salaires
A1: Salaires — Le Yellow Jack
A2: Paye du personnel (barman, videur, gerant...)
A4: Date | B4: Employe | C4: Poste | D4: Heures travaillees | E4: Taux horaire | F4: Total
A5: X | B5: X | C5: Barman | D5: X | E5: X | F5: =IFERROR(IF(D5="","",D5*E5),"")
A6: X | B6: X | C6: Videur | D6: X | E6: X | F6: =IFERROR(IF(D6="","",D6*E6),"")
F7: =IFERROR(IF(D7="","",D7*E7),"")
F8: =IFERROR(IF(D8="","",D8*E8),"")
F9: =IFERROR(IF(D9="","",D9*E9),"")
F10: =IFERROR(IF(D10="","",D10*E10),"")
F11: =IFERROR(IF(D11="","",D11*E11),"")
F12: =IFERROR(IF(D12="","",D12*E12),"")
F13: =IFERROR(IF(D13="","",D13*E13),"")
F14: =IFERROR(IF(D14="","",D14*E14),"")
F15: =IFERROR(IF(D15="","",D15*E15),"")
F16: =IFERROR(IF(D16="","",D16*E16),"")
F17: =IFERROR(IF(D17="","",D17*E17),"")
F18: =IFERROR(IF(D18="","",D18*E18),"")
... F200: =IFERROR(IF(D200="","",D200*E200),"")
E201: TOTAL | F201: =SUM(F5:F200)

Sheet Stock
A1: Stock — Le Yellow Jack
A2: Inventaire des articles vendus au bar
A4: Article | B4: Categorie | C4: Stock actuel | D4: Seuil alerte | E4: Prix d'achat | F4: Prix de vente | G4: Marge / unite
A5: Orange | B5: Boisson | C5: X | D5: X | E5: 10 | F5: X | G5: =IFERROR(IF(A5="","",F5-E5),"")
A6: Whisky | B6: Boisson | C6: X | D6: X | E6: X | F6: X | G6: =IFERROR(IF(A6="","",F6-E6),"")
G7: =IFERROR(IF(A7="","",F7-E7),"")
G8: =IFERROR(IF(A8="","",F8-E8),"")
G9: =IFERROR(IF(A9="","",F9-E9),"")
G10: =IFERROR(IF(A10="","",F10-E10),"")
G11: =IFERROR(IF(A11="","",F11-E11),"")
G12: =IFERROR(IF(A12="","",F12-E12),"")
G13: =IFERROR(IF(A13="","",F13-E13),"")
G14: =IFERROR(IF(A14="","",F14-E14),"")
G15: =IFERROR(IF(A15="","",F15-E15),"")
G16: =IFERROR(IF(A16="","",F16-E16),"")
G17: =IFERROR(IF(A17="","",F17-E17),"")
G18: =IFERROR(IF(A18="","",F18-E18),"")
... G203: =IFERROR(IF(A203="","",F203-E203),"")

Sheet Resume mensuel
A1: Resume mensuel — Le Yellow Jack
A2: Bilan mois par mois, de Janvier a Decembre
A4: Annee analysee : | B4: =YEAR(TODAY()) | C4: (modifie cette cellule si besoin)
A6: Mois | B6: Ventes | C6: Depenses (achats) | D6: Salaires | E6: Total depenses | F6: Benefice net | G6: Marge %
A7: Janvier | B7: =SUMIFS(Ventes!G5:G201,Ventes!A5:A201,">="&DATE($B$4,1,1),Ventes!A5:A201,"<"&DATE($B$4,1+1,1)) | C7: =SUMIFS(Depenses!D5:D201,Depenses!A5:A201,">="&DATE($B$4,1,1),Depenses!A5:A201,"<"&DATE($B$4,1+1,1)) | D7: =SUMIFS(Salaires!F5:F200,Salaires!A5:A200,">="&DATE($B$4,1,1),Salaires!A5:A200,"<"&DATE($B$4,1+1,1)) | E7: =C7+D7 | F7: =B7-E7 | G7: =IFERROR(F7/B7,0)
A8: Fevrier | B8: =SUMIFS(Ventes!G5:G201,Ventes!A5:A201,">="&DATE($B$4,2,1),Ventes!A5:A201,"<"&DATE($B$4,2+1,1)) | C8: =SUMIFS(Depenses!D5:D201,Depenses!A5:A201,">="&DATE($B$4,2,1),Depenses!A5:A201,"<"&DATE($B$4,2+1,1)) | D8: =SUMIFS(Salaires!F5:F200,Salaires!A5:A200,">="&DATE($B$4,2,1),Salaires!A5:A200,"<"&DATE($B$4,2+1,1)) | E8: =C8+D8 | F8: =B8-E8 | G8: =IFERROR(F8/B8,0)
A9: Mars | B9: =SUMIFS(Ventes!G5:G201,Ventes!A5:A201,">="&DATE($B$4,3,1),Ventes!A5:A201,"<"&DATE($B$4,3+1,1)) | C9: =SUMIFS(Depenses!D5:D201,Depenses!A5:A201,">="&DATE($B$4,3,1),Depenses!A5:A201,"<"&DATE($B$4,3+1,1)) | D9: =SUMIFS(Salaires!F5:F200,Salaires!A5:A200,">="&DATE($B$4,3,1),Salaires!A5:A200,"<"&DATE($B$4,3+1,1)) | E9: =C9+D9 | F9: =B9-E9 | G9: =IFERROR(F9/B9,0)
A10: Avril | B10: =SUMIFS(Ventes!G5:G201,Ventes!A5:A201,">="&DATE($B$4,4,1),Ventes!A5:A201,"<"&DATE($B$4,4+1,1)) | C10: =SUMIFS(Depenses!D5:D201,Depenses!A5:A201,">="&DATE($B$4,4,1),Depenses!A5:A201,"<"&DATE($B$4,4+1,1)) | D10: =SUMIFS(Salaires!F5:F200,Salaires!A5:A200,">="&DATE($B$4,4,1),Salaires!A5:A200,"<"&DATE($B$4,4+1,1)) | E10: =C10+D10 | F10: =B10-E10 | G10: =IFERROR(F10/B10,0)
A11: Mai | B11: =SUMIFS(Ventes!G5:G201,Ventes!A5:A201,">="&DATE($B$4,5,1),Ventes!A5:A201,"<"&DATE($B$4,5+1,1)) | C11: =SUMIFS(Depenses!D5:D201,Depenses!A5:A201,">="&DATE($B$4,5,1),Depenses!A5:A201,"<"&DATE($B$4,5+1,1)) | D11: =SUMIFS(Salaires!F5:F200,Salaires!A5:A200,">="&DATE($B$4,5,1),Salaires!A5:A200,"<"&DATE($B$4,5+1,1)) | E11: =C11+D11 | F11: =B11-E11 | G11: =IFERROR(F11/B11,0)
A12: Juin | B12: =SUMIFS(Ventes!G5:G201,Ventes!A5:A201,">="&DATE($B$4,6,1),Ventes!A5:A201,"<"&DATE($B$4,6+1,1)) | C12: =SUMIFS(Depenses!D5:D201,Depenses!A5:A201,">="&DATE($B$4,6,1),Depenses!A5:A201,"<"&DATE($B$4,6+1,1)) | D12: =SUMIFS(Salaires!F5:F200,Salaires!A5:A200,">="&DATE($B$4,6,1),Salaires!A5:A200,"<"&DATE($B$4,6+1,1)) | E12: =C12+D12 | F12: =B12-E12 | G12: =IFERROR(F12/B12,0)
A13: Juillet | B13: =SUMIFS(Ventes!G5:G201,Ventes!A5:A201,">="&DATE($B$4,7,1),Ventes!A5:A201,"<"&DATE($B$4,7+1,1)) | C13: =SUMIFS(Depenses!D5:D201,Depenses!A5:A201,">="&DATE($B$4,7,1),Depenses!A5:A201,"<"&DATE($B$4,7+1,1)) | D13: =SUMIFS(Salaires!F5:F200,Salaires!A5:A200,">="&DATE($B$4,7,1),Salaires!A5:A200,"<"&DATE($B$4,7+1,1)) | E13: =C13+D13 | F13: =B13-E13 | G13: =IFERROR(F13/B13,0)
A14: Aout | B14: =SUMIFS(Ventes!G5:G201,Ventes!A5:A201,">="&DATE($B$4,8,1),Ventes!A5:A201,"<"&DATE($B$4,8+1,1)) | C14: =SUMIFS(Depenses!D5:D201,Depenses!A5:A201,">="&DATE($B$4,8,1),Depenses!A5:A201,"<"&DATE($B$4,8+1,1)) | D14: =SUMIFS(Salaires!F5:F200,Salaires!A5:A200,">="&DATE($B$4,8,1),Salaires!A5:A200,"<"&DATE($B$4,8+1,1)) | E14: =C14+D14 | F14: =B14-E14 | G14: =IFERROR(F14/B14,0)
A15: Septembre | B15: =SUMIFS(Ventes!G5:G201,Ventes!A5:A201,">="&DATE($B$4,9,1),Ventes!A5:A201,"<"&DATE($B$4,9+1,1)) | C15: =SUMIFS(Depenses!D5:D201,Depenses!A5:A201,">="&DATE($B$4,9,1),Depenses!A5:A201,"<"&DATE($B$4,9+1,1)) | D15: =SUMIFS(Salaires!F5:F200,Salaires!A5:A200,">="&DATE($B$4,9,1),Salaires!A5:A200,"<"&DATE($B$4,9+1,1)) | E15: =C15+D15 | F15: =B15-E15 | G15: =IFERROR(F15/B15,0)
A16: Octobre | B16: =SUMIFS(Ventes!G5:G201,Ventes!A5:A201,">="&DATE($B$4,10,1),Ventes!A5:A201,"<"&DATE($B$4,10+1,1)) | C16: =SUMIFS(Depenses!D5:D201,Depenses!A5:A201,">="&DATE($B$4,10,1),Depenses!A5:A201,"<"&DATE($B$4,10+1,1)) | D16: =SUMIFS(Salaires!F5:F200,Salaires!A5:A200,">="&DATE($B$4,10,1),Salaires!A5:A200,"<"&DATE($B$4,10+1,1)) | E16: =C16+D16 | F16: =B16-E16 | G16: =IFERROR(F16/B16,0)
A17: Novembre | B17: =SUMIFS(Ventes!G5:G201,Ventes!A5:A201,">="&DATE($B$4,11,1),Ventes!A5:A201,"<"&DATE($B$4,11+1,1)) | C17: =SUMIFS(Depenses!D5:D201,Depenses!A5:A201,">="&DATE($B$4,11,1),Depenses!A5:A201,"<"&DATE($B$4,11+1,1)) | D17: =SUMIFS(Salaires!F5:F200,Salaires!A5:A200,">="&DATE($B$4,11,1),Salaires!A5:A200,"<"&DATE($B$4,11+1,1)) | E17: =C17+D17 | F17: =B17-E17 | G17: =IFERROR(F17/B17,0)
A18: Decembre | B18: =SUMIFS(Ventes!G5:G201,Ventes!A5:A201,">="&DATE($B$4,12,1),Ventes!A5:A201,"<"&DATE($B$4,12+1,1)) | C18: =SUMIFS(Depenses!D5:D201,Depenses!A5:A201,">="&DATE($B$4,12,1),Depenses!A5:A201,"<"&DATE($B$4,12+1,1)) | D18: =SUMIFS(Salaires!F5:F200,Salaires!A5:A200,">="&DATE($B$4,12,1),Salaires!A5:A200,"<"&DATE($B$4,12+1,1)) | E18: =C18+D18 | F18: =B18-E18 | G18: =IFERROR(F18/B18,0)
A19: TOTAL ANNEE | B19: =SUM(B7:B18) | C19: =SUM(C7:C18) | D19: =SUM(D7:D18) | E19: =SUM(E7:E18) | F19: =SUM(F7:F18) | G19: =IFERROR(F19/B19,0)
